dfttoolkit/__init__.py
dfttoolkit/base.py
dfttoolkit/benchmarking.py
dfttoolkit/cube.py
dfttoolkit/custom_ase.py
dfttoolkit/friction.py
dfttoolkit/geometry.py
dfttoolkit/output.py
dfttoolkit/parameters.py
dfttoolkit/trajectory.py
dfttoolkit/vibrations.py
dfttoolkit/visualise.py
dfttoolkit/utils/__init__.py
dfttoolkit/utils/covalent_radii.yaml
dfttoolkit/utils/elemental_colourmaps.yaml
dfttoolkit/utils/exceptions.py
dfttoolkit/utils/file_crawler.py
dfttoolkit/utils/file_utils.py
dfttoolkit/utils/geometry_utils.py
dfttoolkit/utils/math_utils.py
dfttoolkit/utils/periodic_table.py
dfttoolkit/utils/periodic_table.yaml
dfttoolkit/utils/run_utils.py
dfttoolkit/utils/units.py
dfttoolkit/utils/vibrations_utils.py
dfttoolkit-0.4.0.dist-info/METADATA
dfttoolkit-0.4.0.dist-info/WHEEL
dfttoolkit-0.4.0.dist-info/licenses/LICENSE
dfttoolkit-0.4.0.dist-info/RECORD
