Metadata-Version: 2.4
Name: dfttoolkit
Version: 0.4.0
Summary: A collection of python modules and libraries for several DFT codes to handle input, output, and post-processing.
Project-URL: Documentation, https://maurergroup.github.io/dfttoolkit/
Project-URL: Repository, https://github.com/maurergroup/dfttoolkit
Project-URL: Issues, https://github.com/maurergroup/dfttoolkit/issues
Author-email: Dylan Morgan <dylan.morgan@warwick.ac.uk>, Lukas Hoermann <lukas.hoermann@warwick.ac.uk>
Maintainer-email: Dylan Morgan <dylan.morgan@warwick.ac.uk>, Lukas Hoermann <lukas.hoermann@warwick.ac.uk>
License-Expression: GPL-3.0-or-later
License-File: LICENSE
Requires-Python: <3.14,>=3.11
Requires-Dist: ase>=3.22.1
Requires-Dist: click>=8.2.1
Requires-Dist: ipython>=9.2.0
Requires-Dist: marimo>=0.13.11
Requires-Dist: matplotlib>=3.10.3
Requires-Dist: networkx>=3.4.2
Requires-Dist: numba>=0.61.2
Requires-Dist: numpy>=2.2.6
Requires-Dist: pyside6>=6.9.1
Requires-Dist: pyyaml>=6.0.2
Requires-Dist: scipy>=1.15.3
Requires-Dist: spglib>=2.6.0
Requires-Dist: weas-widget>=0.1.26
